pypixelai/__init__.py
pypixelai/constants.py
pypixelai/exceptions.py
pypixelai/models/__init__.py
pypixelai/models/base.py
pypixelai/models/cohere.py
pypixelai/models/openai.py
pypixelai/models/starcoder.py
pypixelai/prompts/__init__.py
pypixelai/prompts/edit_image.py
pypixelai/prompts/fix_errors.py
pypixelai/prompts/generate_code.py
pypixelai/prompts/generate_image.py
pypixelai/prompts/prompt.py
pypixelai-0.2.1.dist-info/LICENSE
pypixelai-0.2.1.dist-info/METADATA
pypixelai-0.2.1.dist-info/WHEEL
pypixelai-0.2.1.dist-info/RECORD
