Metadata-Version: 2.1
Name: pypixelai
Version: 0.2.1
Summary: Image processing made easy
Author: Navneet Desai
Author-email: navneetdesai44@gmail.com
Requires-Python: >=3.9,<4.0
Classifier: Programming Language :: Python :: 3
Classifier: Programming Language :: Python :: 3.9
Classifier: Programming Language :: Python :: 3.10
Classifier: Programming Language :: Python :: 3.11
Requires-Dist: black (>=23.3.0,<24.0.0)
Requires-Dist: cohere (>=4.6.0,<5.0.0)
Requires-Dist: isort (>=5.12.0,<6.0.0)
Requires-Dist: logging (>=0.4.9.6,<0.5.0.0)
Requires-Dist: mahotas (>=1.4.13,<2.0.0)
Requires-Dist: matplotlib (>=3.7.1,<4.0.0)
Requires-Dist: numpy (>=1.24.3,<2.0.0)
Requires-Dist: openai (>=0.27.7,<0.28.0)
Requires-Dist: opencv-python (>=4.7.0.72,<5.0.0.0)
Requires-Dist: pre-commit (>=3.3.2,<4.0.0)
Requires-Dist: pyflakes (>=3.0.1,<4.0.0)
Requires-Dist: pylint (>=2.17.4,<3.0.0)
Requires-Dist: pytest (>=7.3.1,<8.0.0)
Requires-Dist: pytest-cov (>=4.1.0,<5.0.0)
Requires-Dist: pytest-mock (>=3.10.0,<4.0.0)
Requires-Dist: python-dotenv (>=1.0.0,<2.0.0)
Requires-Dist: requests (>=2.31.0,<3.0.0)
